pubpub/__init__.py
pubpub/browser.py
pubpub/bundle.py
pubpub/config.py
pubpub/filters.py
pubpub/processor.py
pubpub/utils.py
pubpub/cli/__init__.py
pubpub/cli/cli.py
pubpub/cli/commands.py
pubpub/resources/__init__.py
pubpub/runners/__init__.py
pubpub/runners/run_to_html.py
pubpub/runners/run_to_latex.py
pubpub/templates/__init__.py
pubpub/templates/base.py
pubpub/templates/html.py
pubpub/templates/latex.py
pubpub/templates/pdf.py
pubpub-0.0.29.dev1.dist-info/DESCRIPTION.rst
pubpub-0.0.29.dev1.dist-info/METADATA
pubpub-0.0.29.dev1.dist-info/RECORD
pubpub-0.0.29.dev1.dist-info/WHEEL
pubpub-0.0.29.dev1.dist-info/entry_points.txt
pubpub-0.0.29.dev1.dist-info/metadata.json
pubpub-0.0.29.dev1.dist-info/pbr.json
pubpub-0.0.29.dev1.dist-info/top_level.txt
