Metadata-Version: 2.0
Name: pubpub
Version: 0.0.29.dev1
Summary: "A package to turn jupyter notebooks into pdfs"
Home-page: UNKNOWN
Author: UNKNOWN
Author-email: ari@fullstack.io
License: BSD
Platform: UNKNOWN
Requires-Dist: Click
Requires-Dist: Jinja2
Requires-Dist: markdown
Requires-Dist: pbr
Requires-Dist: pip
Requires-Dist: pyScss
Requires-Dist: python-frontmatter
Requires-Dist: selenium
Requires-Dist: setuptools
Requires-Dist: versioneer
